{"time":"2022-08-27T21:11:00","unixTime":1661605860,"fResult":[{"id":2,"votes":0.0895,"rank":5},{"id":3,"votes":0.0969,"rank":2},{"id":4,"votes":0.134,"rank":1},{"id":6,"votes":0.0891,"rank":8},{"id":7,"votes":0.0891,"rank":9},{"id":12,"votes":0.1382,"rank":0},{"id":14,"votes":0.0892,"rank":7},{"id":15,"votes":0.0893,"rank":6},{"id":17,"votes":0.0941,"rank":3},{"id":26,"votes":0.0906,"rank":4}],"mResult":[{"id":27,"votes":0.0843,"rank":10},{"id":28,"votes":0.0981,"rank":1},{"id":32,"votes":0.0924,"rank":2},{"id":33,"votes":0.089,"rank":4},{"id":34,"votes":0.0896,"rank":3},{"id":37,"votes":0.0888,"rank":7},{"id":43,"votes":0.1026,"rank":0},{"id":45,"votes":0.0887,"rank":9},{"id":46,"votes":0.0888,"rank":8},{"id":49,"votes":0.0889,"rank":5},{"id":51,"votes":0.0889,"rank":6}]}