{"time":"2022-08-28T13:10:00","unixTime":1661663400,"fResult":[{"id":2,"votes":0.1225,"rank":4},{"id":3,"votes":0.1164,"rank":5},{"id":4,"votes":0.1391,"rank":1},{"id":6,"votes":0.0772,"rank":6},{"id":7,"votes":0.0735,"rank":7},{"id":12,"votes":0.1556,"rank":0},{"id":14,"votes":0.0607,"rank":8},{"id":17,"votes":0.1244,"rank":3},{"id":26,"votes":0.1305,"rank":2}],"mResult":[{"id":27,"votes":0.1184,"rank":3},{"id":28,"votes":0.1129,"rank":4},{"id":32,"votes":0.13,"rank":1},{"id":34,"votes":0.1081,"rank":6},{"id":37,"votes":0.1087,"rank":5},{"id":43,"votes":0.1587,"rank":0},{"id":45,"votes":0.0842,"rank":7},{"id":46,"votes":0.0556,"rank":8},{"id":49,"votes":0.1233,"rank":2}]}