{"time":"2022-08-28T12:59:00","unixTime":1661662740,"fResult":[{"id":2,"votes":0.1199,"rank":4},{"id":3,"votes":0.1199,"rank":5},{"id":4,"votes":0.1387,"rank":1},{"id":6,"votes":0.081,"rank":6},{"id":7,"votes":0.0712,"rank":7},{"id":12,"votes":0.1619,"rank":0},{"id":14,"votes":0.0622,"rank":8},{"id":17,"votes":0.1222,"rank":3},{"id":26,"votes":0.1229,"rank":2}],"mResult":[{"id":27,"votes":0.1201,"rank":3},{"id":28,"votes":0.1088,"rank":4},{"id":32,"votes":0.1307,"rank":1},{"id":34,"votes":0.108,"rank":5},{"id":37,"votes":0.1057,"rank":6},{"id":43,"votes":0.1594,"rank":0},{"id":45,"votes":0.0884,"rank":7},{"id":46,"votes":0.0544,"rank":8},{"id":49,"votes":0.1246,"rank":2}]}