{"time":"2022-09-05T01:45:00","unixTime":1662313500,"fResult":[{"id":2,"votes":0.1125,"rank":5},{"id":3,"votes":0.1501,"rank":1},{"id":4,"votes":0.1308,"rank":2},{"id":7,"votes":0.1103,"rank":6},{"id":12,"votes":0.1568,"rank":0},{"id":14,"votes":0.1129,"rank":4},{"id":17,"votes":0.1179,"rank":3},{"id":26,"votes":0.1088,"rank":7}],"mResult":[{"id":27,"votes":0.0861,"rank":6},{"id":28,"votes":0.1429,"rank":2},{"id":32,"votes":0.1395,"rank":3},{"id":34,"votes":0.1333,"rank":4},{"id":37,"votes":0.1744,"rank":0},{"id":43,"votes":0.1451,"rank":1},{"id":46,"votes":0.0632,"rank":7},{"id":49,"votes":0.1156,"rank":5}]}