{"time":"2022-09-14T11:59:00","unixTime":1663127940,"fResult":[{"id":2,"votes":0.1158,"rank":6},{"id":3,"votes":0.1777,"rank":0},{"id":4,"votes":0.1445,"rank":3},{"id":7,"votes":0.1318,"rank":4},{"id":12,"votes":0.1602,"rank":1},{"id":17,"votes":0.1208,"rank":5},{"id":26,"votes":0.1492,"rank":2}],"mResult":[{"id":27,"votes":0.1457,"rank":2},{"id":28,"votes":0.1471,"rank":1},{"id":32,"votes":0.1168,"rank":6},{"id":34,"votes":0.1251,"rank":5},{"id":37,"votes":0.196,"rank":0},{"id":43,"votes":0.1439,"rank":3},{"id":49,"votes":0.1255,"rank":4}]}