{"time":"2022-08-11T22:52:03","unixTime":1660229523,"fResult":[{"id":2,"voteId":"Cg-_0RuJYu4","likes":12128},{"id":3,"voteId":"Cg-_87JpIKz","likes":6069},{"id":4,"voteId":"Cg_AGOtJ_JA","likes":8828},{"id":5,"voteId":"Cg_AKGcJyOi","likes":2644},{"id":6,"voteId":"Cg_APB5Jhw-","likes":7116},{"id":7,"voteId":"Cg_Acy0JaV5","likes":8870},{"id":9,"voteId":"Cg_AhrXJ1W4","likes":3062},{"id":12,"voteId":"Cg_AmJAJdax","likes":24659},{"id":14,"voteId":"Cg_AykCp2AQ","likes":7555},{"id":15,"voteId":"Cg_A16bJmNr","likes":5995},{"id":17,"voteId":"Cg_BCgKJSB_","likes":11353},{"id":20,"voteId":"Cg_BIYgJVXG","likes":5061},{"id":22,"voteId":"Cg_DiRjPDII","likes":4628},{"id":25,"voteId":"Cg_DsyxvBdY","likes":6112},{"id":26,"voteId":"Cg_D4nbvGtY","likes":9543}],"mResult":[{"id":27,"voteId":"Cg_EBR5PDd3","likes":6017},{"id":28,"voteId":"Cg_FBsfF1jR","likes":13860},{"id":30,"voteId":"Cg_FIY-l8IA","likes":5003},{"id":32,"voteId":"Cg_FNVllyob","likes":9833},{"id":33,"voteId":"Cg_FSZ1lkRM","likes":6186},{"id":34,"voteId":"Cg_FdifFRjt","likes":8107},{"id":36,"voteId":"Cg_FitVl8IC","likes":5664},{"id":37,"voteId":"Cg_Fql0l0Zx","likes":6115},{"id":40,"voteId":"Cg_FwAUFxpK","likes":2334},{"id":42,"voteId":"Cg_F7roFzi7","likes":2696},{"id":43,"voteId":"Cg_GAmcFbQr","likes":6675},{"id":45,"voteId":"Cg_GJFSFtgU","likes":10924},{"id":46,"voteId":"Cg_GOG2lqjm","likes":10091},{"id":49,"voteId":"Cg_GY92l8WL","likes":7236},{"id":51,"voteId":"Cg_GdSyltMe","likes":13692}]}