{"time":"2022-08-11T08:51:34","unixTime":1660179094,"fResult":[{"id":2,"voteId":"Cg-_0RuJYu4","likes":10315},{"id":3,"voteId":"Cg-_87JpIKz","likes":5205},{"id":4,"voteId":"Cg_AGOtJ_JA","likes":7631},{"id":5,"voteId":"Cg_AKGcJyOi","likes":2375},{"id":6,"voteId":"Cg_APB5Jhw-","likes":6696},{"id":7,"voteId":"Cg_Acy0JaV5","likes":8405},{"id":9,"voteId":"Cg_AhrXJ1W4","likes":2641},{"id":12,"voteId":"Cg_AmJAJdax","likes":13619},{"id":14,"voteId":"Cg_AykCp2AQ","likes":6676},{"id":15,"voteId":"Cg_A16bJmNr","likes":5142},{"id":17,"voteId":"Cg_BCgKJSB_","likes":10287},{"id":20,"voteId":"Cg_BIYgJVXG","likes":4094},{"id":22,"voteId":"Cg_DiRjPDII","likes":4245},{"id":25,"voteId":"Cg_DsyxvBdY","likes":5805},{"id":26,"voteId":"Cg_D4nbvGtY","likes":9009}],"mResult":[{"id":27,"voteId":"Cg_EBR5PDd3","likes":5542},{"id":28,"voteId":"Cg_FBsfF1jR","likes":13167},{"id":30,"voteId":"Cg_FIY-l8IA","likes":4829},{"id":32,"voteId":"Cg_FNVllyob","likes":9490},{"id":33,"voteId":"Cg_FSZ1lkRM","likes":5957},{"id":34,"voteId":"Cg_FdifFRjt","likes":7763},{"id":36,"voteId":"Cg_FitVl8IC","likes":5446},{"id":37,"voteId":"Cg_Fql0l0Zx","likes":5861},{"id":40,"voteId":"Cg_FwAUFxpK","likes":2225},{"id":42,"voteId":"Cg_F7roFzi7","likes":2560},{"id":43,"voteId":"Cg_GAmcFbQr","likes":6316},{"id":45,"voteId":"Cg_GJFSFtgU","likes":10495},{"id":46,"voteId":"Cg_GOG2lqjm","likes":9681},{"id":49,"voteId":"Cg_GY92l8WL","likes":6911},{"id":51,"voteId":"Cg_GdSyltMe","likes":13221}]}